seqcalc.py
seqcalc-0.0.2.dist-info/licenses/LICENSE
seqcalc-0.0.2.dist-info/METADATA
seqcalc-0.0.2.dist-info/WHEEL
seqcalc-0.0.2.dist-info/top_level.txt
seqcalc-0.0.2.dist-info/RECORD
