Metadata-Version: 2.4
Name: seqcalc
Version: 0.0.2
Summary: Arithmetic sequence calculator
Author-email: ryuzen06 <ziel26314@gmail.com>
License-Expression: MIT
Classifier: Programming Language :: Python :: 3
Classifier: Operating System :: OS Independent
Requires-Python: >=3.9
License-File: LICENSE
Dynamic: license-file
